maheer/__init__.py
maheer/core.py
maheer-1.0.1.dist-info/METADATA
maheer-1.0.1.dist-info/WHEEL
maheer-1.0.1.dist-info/top_level.txt
maheer-1.0.1.dist-info/RECORD
