Metadata-Version: 2.4
Name: maheer
Version: 1.0.1
Summary: Coming Soon
Author: Akbar
Author-email: akbarali10143@gmail.com
Classifier: Programming Language :: Python :: 3
Classifier: License :: OSI Approved :: MIT License
Requires-Python: >=3.6
Dynamic: author
Dynamic: author-email
Dynamic: classifier
Dynamic: requires-python
Dynamic: summary
